oaipmh_scythe/__about__.py
oaipmh_scythe/__init__.py
oaipmh_scythe/client.py
oaipmh_scythe/exceptions.py
oaipmh_scythe/iterator.py
oaipmh_scythe/models.py
oaipmh_scythe/py.typed
oaipmh_scythe/response.py
oaipmh_scythe/utils.py
oaipmh_scythe-0.13.0.dist-info/METADATA
oaipmh_scythe-0.13.0.dist-info/WHEEL
oaipmh_scythe-0.13.0.dist-info/licenses/AUTHORS.md
oaipmh_scythe-0.13.0.dist-info/licenses/LICENSE
oaipmh_scythe-0.13.0.dist-info/RECORD
